autodistill_distilbert/__init__.py
autodistill_distilbert/model.py
autodistill_distilbert-0.1.0.dist-info/LICENSE
autodistill_distilbert-0.1.0.dist-info/METADATA
autodistill_distilbert-0.1.0.dist-info/WHEEL
autodistill_distilbert-0.1.0.dist-info/top_level.txt
autodistill_distilbert-0.1.0.dist-info/RECORD
