Metadata-Version: 2.1
Name: autodistill-distilbert
Version: 0.1.0
Summary: DistilBERT model for use with Autodistill
Home-page: https://github.com/autodistill/autodistill-distilbert
Author: capjamesg
Author-email: support@roboflow.com
Classifier: Programming Language :: Python :: 3
Classifier: License :: OSI Approved :: MIT License
Classifier: Operating System :: OS Independent
Requires-Python: >=3.7
License-File: LICENSE
Requires-Dist: datasets
Requires-Dist: autodistill
Requires-Dist: transformers
Requires-Dist: evaluate
Requires-Dist: numpy
Provides-Extra: dev
Requires-Dist: flake8 ; extra == 'dev'
Requires-Dist: black ==22.3.0 ; extra == 'dev'
Requires-Dist: isort ; extra == 'dev'
Requires-Dist: twine ; extra == 'dev'
Requires-Dist: pytest ; extra == 'dev'
Requires-Dist: wheel ; extra == 'dev'
